CONTRIBUTING.md
Jenkinsfile
MANIFEST.in
README.rst
setup.py
buildouts/plone4/buildout.cfg
buildouts/plone4/install.sh
buildouts/plone4/versions.cfg
buildouts/zope2/buildout.cfg
buildouts/zope2/install.sh
buildouts/zope2/versions.cfg
docs/HISTORY.txt
docs/LICENSE.GPL
docs/LICENSE.txt
eea/__init__.py
eea.exhibit.egg-info/PKG-INFO
eea.exhibit.egg-info/SOURCES.txt
eea.exhibit.egg-info/dependency_links.txt
eea.exhibit.egg-info/entry_points.txt
eea.exhibit.egg-info/namespace_packages.txt
eea.exhibit.egg-info/not-zip-safe
eea.exhibit.egg-info/requires.txt
eea.exhibit.egg-info/top_level.txt
eea/exhibit/README.txt
eea/exhibit/__init__.py
eea/exhibit/common.zcml
eea/exhibit/configure.zcml
eea/exhibit/meta.zcml
eea/exhibit/plone.zcml
eea/exhibit/profiles.zcml
eea/exhibit/version.txt
eea/exhibit/zope2.zcml
eea/exhibit/babel/__init__.py
eea/exhibit/babel/configure.zcml
eea/exhibit/babel/interfaces.py
eea/exhibit/babel/rdfxml.py
eea/exhibit/babel/translator.py
eea/exhibit/babel/writer.py
eea/exhibit/browser/__init__.py
eea/exhibit/browser/configure.zcml
eea/exhibit/browser/app/__init__.py
eea/exhibit/browser/app/view.py
eea/exhibit/browser/css/edit.css
eea/exhibit/browser/css/view.css
eea/exhibit/browser/js/edit.js
eea/exhibit/browser/js/view.js
eea/exhibit/browser/res/__init__.py
eea/exhibit/browser/res/configure.zcml
eea/exhibit/browser/res/resources.py
eea/exhibit/browser/zpt/head.pt
eea/exhibit/controlpanel/__init__.py
eea/exhibit/controlpanel/configure.zcml
eea/exhibit/controlpanel/controlpanel.py
eea/exhibit/facets/__init__.py
eea/exhibit/facets/configure.zcml
eea/exhibit/facets/alphabetical/__init__.py
eea/exhibit/facets/alphabetical/configure.zcml
eea/exhibit/facets/alphabetical/edit.py
eea/exhibit/facets/alphabetical/interfaces.py
eea/exhibit/facets/alphabetical/view.py
eea/exhibit/facets/cloud/__init__.py
eea/exhibit/facets/cloud/configure.zcml
eea/exhibit/facets/cloud/edit.py
eea/exhibit/facets/cloud/interfaces.py
eea/exhibit/facets/cloud/view.py
eea/exhibit/facets/hierarchical/__init__.py
eea/exhibit/facets/hierarchical/configure.zcml
eea/exhibit/facets/hierarchical/edit.py
eea/exhibit/facets/hierarchical/interfaces.py
eea/exhibit/facets/hierarchical/view.py
eea/exhibit/facets/numeric/__init__.py
eea/exhibit/facets/numeric/configure.zcml
